src/__init__.py
src/basechatevent.py
src/chatlistresponse.py
src/chatresponse.py
src/createchatrequest.py
src/errorchunk.py
src/errorresponse.py
src/index.py
src/inputmessage.py
src/listchatsrequest.py
src/messagechunk.py
src/messageresponse.py
src/paginationparams.py
src/paginationresponse.py
src/paginationresponse_chatresponse_.py
src/sendmessagerequest.py
src/stream_event.py
src/suggestionchunk.py
src/thinkingchunk.py
src/timestamp.py
src/toolcallchunk.py
src/updatechatrequest.py
src/utils.py
carv_chat_schemas-3.1.1.dist-info/METADATA
carv_chat_schemas-3.1.1.dist-info/WHEEL
carv_chat_schemas-3.1.1.dist-info/RECORD
