Metadata-Version: 2.4
Name: carv-chat-schemas
Version: 3.1.1
Summary: Pydantic v2 models for chat API, automatically generated from JSON schemas
Project-URL: Homepage, https://github.com/carv-app/carv-recruiter-schema
Project-URL: Repository, https://github.com/carv-app/carv-recruiter-schema
Project-URL: Documentation, https://github.com/carv-app/carv-recruiter-schema
Author: Carv
License: ISC
Keywords: api,chat,json-schema,pydantic,schemas,types,validation
Classifier: Development Status :: 4 - Beta
Classifier: Intended Audience :: Developers
Classifier: License :: OSI Approved
Classifier: Programming Language :: Python :: 3
Classifier: Programming Language :: Python :: 3.9
Classifier: Programming Language :: Python :: 3.10
Classifier: Programming Language :: Python :: 3.11
Classifier: Programming Language :: Python :: 3.12
Classifier: Typing :: Typed
Requires-Python: >=3.9
Requires-Dist: pydantic>=2.0.0
